INSTALL
KNOWN_BUGS
LICENSE
MANIFEST.in
README.rst
README.txt
THANKS.txt
requires.txt
setup.cfg
setup.py
SphinxReport/Cache.py
SphinxReport/Component.py
SphinxReport/Config.py
SphinxReport/CorrespondenceAnalysis.py
SphinxReport/DataTree.py
SphinxReport/DataTypes.py
SphinxReport/Dispatcher.py
SphinxReport/Histogram.py
SphinxReport/Logger.py
SphinxReport/Logger_test.py
SphinxReport/ResultBlock.py
SphinxReport/SQLDatabase.py
SphinxReport/Stats.py
SphinxReport/Tracker.py
SphinxReport/Utils.py
SphinxReport/__init__.py
SphinxReport/build.py
SphinxReport/clean.py
SphinxReport/errors_directive.py
SphinxReport/gallery.py
SphinxReport/get.py
SphinxReport/only_directives.py
SphinxReport/profile.py
SphinxReport/quickstart.py
SphinxReport/report_directive.py
SphinxReport/roles.py
SphinxReport/serve.py
SphinxReport/test.py
SphinxReport/warnings_directive.py
SphinxReport.egg-info/PKG-INFO
SphinxReport.egg-info/SOURCES.txt
SphinxReport.egg-info/dependency_links.txt
SphinxReport.egg-info/entry_points.txt
SphinxReport.egg-info/not-zip-safe
SphinxReport.egg-info/requires.txt
SphinxReport.egg-info/top_level.txt
SphinxReportPlugins/BokehPlotter.py
SphinxReportPlugins/GGPlotter.py
SphinxReportPlugins/Plotter.py
SphinxReportPlugins/RPlotter.py
SphinxReportPlugins/Renderer.py
SphinxReportPlugins/Transformer.py
SphinxReportPlugins/TransformersGeneLists.py
SphinxReportPlugins/__init__.py
SphinxReportPlugins/BokehPlugin/__init__.py
SphinxReportPlugins/HTMLPlugin/__init__.py
SphinxReportPlugins/MatplotlibPlugin/__init__.py
SphinxReportPlugins/RPlotPlugin/__init__.py
SphinxReportPlugins/RSTPlugin/__init__.py
SphinxReportPlugins/XLSPlugin/__init__.py
doc/Advanced.rst
doc/Background.rst
doc/ComplexDocuments.rst
doc/DataTypes.rst
doc/Developing.rst
doc/Errors.rst
doc/FAQ.rst
doc/GalleryBarplots.rst
doc/GalleryBokeh.rst
doc/GalleryBoxPlots.rst
doc/GalleryConfig.rst
doc/GalleryDebug.rst
doc/GalleryDensityPlots.rst
doc/GalleryGGPlot.rst
doc/GalleryGallery.rst
doc/GalleryHistograms.rst
doc/GalleryLayout.rst
doc/GalleryLegends.rst
doc/GalleryLinePlots.rst
doc/GalleryMatrices.rst
doc/GalleryOptions.rst
doc/GalleryPiePlots.rst
doc/GalleryRPlots.rst
doc/GalleryScatterPlots.rst
doc/GalleryStatus.rst
doc/GalleryTables.rst
doc/GalleryUser.rst
