Metadata-Version: 1.0
Name: SphinxReport
Version: 2.4.1
Summary: SphinxReport : a report generator in python based on Sphinx and matplotlib
Home-page: http://code.google.com/p/sphinx-report/
Author: Andreas Heger
Author-email: andreas.heger@gmail.com
License: BSD
Keywords: report generator sphinx matplotlib sql
Platform: any
Classifier: Development Status :: 4 - Beta
Classifier: Intended Audience :: Science/Research
Classifier: Intended Audience :: Developers
Classifier: License :: OSI Approved
Classifier: Programming Language :: Python
Classifier: Topic :: Software Development
Classifier: Topic :: Scientific/Engineering
Classifier: Operating System :: Microsoft :: Windows
Classifier: Operating System :: POSIX
Classifier: Operating System :: Unix
Classifier: Operating System :: MacOS
